JK/__init__.py
JK/db.py
JK/file.py
JK/image.py
JK/telegram_bot.py
JK/web.py
azunyan-4.10.0.dist-info/LICENSE
azunyan-4.10.0.dist-info/METADATA
azunyan-4.10.0.dist-info/WHEEL
azunyan-4.10.0.dist-info/top_level.txt
azunyan-4.10.0.dist-info/RECORD
