Metadata-Version: 2.1
Name: azunyan
Version: 4.10.0
Summary: Some simple functions I packed for self usage
Home-page: https://github.com/Elypha/azunyan
Author: Elypha
Author-email: i@elypha.com
Project-URL: Bug Tracker, https://github.com/Elypha/azunyan/issues
Classifier: Programming Language :: Python :: 3
Classifier: License :: OSI Approved :: GNU General Public License v3 or later (GPLv3+)
Classifier: Operating System :: OS Independent
Requires-Python: >=3.9
License-File: LICENSE
